[
    {
        "title": "애플, EU집행위 제소…'아이폰 생태계' 개방 명령 부당",
        "date": "2025-06-03 02:08",
        "link": "https://n.news.naver.com/mnews/article/422/0000746170?sid=101"
    },
    {
        "title": "애플, EU집행위 제소…'아이폰 생태계' 개방 명령 부당",
        "date": "2025-06-03 02:01",
        "link": "https://n.news.naver.com/mnews/article/001/0015428007?sid=104"
    },
    {
        "title": "바이블 애플, 글로벌 버전 출시…국내 최초로 ESV·NASB 무료 제공",
        "date": "2025-06-02 23:30",
        "link": "https://www.goodnews1.com/news/articleView.html?idxno=448154"
    },
    {
        "title": "중남미 이어 안방서도 선두 유지… 보급형 '갤 A36' 뜬다",
        "date": "2025-06-02 18:27",
        "link": "https://n.news.naver.com/mnews/article/014/0005358278?sid=105"
    },
    {
        "title": "애플, 오픈AI 맞먹는 150B 추론 모델 개발...출시는 미정",
        "date": "2025-06-02 18:00",
        "link": "https://www.aitimes.com/news/articleView.html?idxno=170969"
    },
    {
        "title": "구글·애플 앱마켓 게임사 수수료 인하 美 집단조정 설명회 성료…100여...",
        "date": "2025-06-02 17:58",
        "link": "https://www.youthdaily.co.kr/news/article.html?no=186515"
    },
    {
        "title": "공급망 타격 흔들리는 애플…AI 앞세워 치고나간 샤오미",
        "date": "2025-06-02 17:49",
        "link": "https://n.news.naver.com/mnews/article/011/0004492752?sid=104"
    },
    {
        "title": "트럼프 관세에 스마트폰 희비… 아이폰 '미소' 갤럭시 '씁쓸'",
        "date": "2025-06-02 17:44",
        "link": "https://www.asiatoday.co.kr/view.php?key=20250603010000843"
    },
    {
        "title": "중국산 ESP32 칩, 주요 암호화폐 지갑 노리는 심각한 보안 취약점 발견",
        "date": "2025-06-02 17:28",
        "link": "https://www.tokenpost.kr/news/blockchain/238864"
    },
    {
        "title": "애플 EU의 '경쟁사 기기 호환' 명령에 항소, 개인정보와 지재권 침해 ...",
        "date": "2025-06-02 17:08",
        "link": "https://www.businesspost.co.kr/BP?command=article_view&num=397671"
    },
    {
        "title": "비전옥스, IT 8세대 투자 우선순위 'ViP'로 선회...FMM 연기",
        "date": "2025-06-02 16:58",
        "link": "http://www.thelec.kr/news/articleView.html?idxno=36653"
    },
    {
        "title": "자바와 마이SQL 30주년, 서른 즈음에",
        "date": "2025-06-02 16:46",
        "link": "https://byline.network/?p=9004111222566269"
    },
    {
        "title": "암호화폐 결제 플랫폼 메시, 애플페이 통합 기능 공개…2분기 후반 출시...",
        "date": "2025-06-02 16:40",
        "link": "https://www.tokenpost.kr/news/blockchain/243822"
    },
    {
        "title": "애플 아이폰17e 준비 중…출시 전략 변화",
        "date": "2025-06-02 16:37",
        "link": "https://n.news.naver.com/mnews/article/092/0002376765?sid=105"
    },
    {
        "title": "에픽게임즈, 애플 상대로 승소...iOS 앱 내 암호화폐 결제 제한 해제 전...",
        "date": "2025-06-02 16:30",
        "link": "https://www.tokenpost.kr/news/blockchain/244364"
    },
    {
        "title": "애플 AI 또 밀린다…건강 AI '멀버리'도 올해 WWDC엔 없을 것",
        "date": "2025-06-02 16:16",
        "link": "https://n.news.naver.com/mnews/article/421/0008290143?sid=105"
    },
    {
        "title": "중남미 1위 지킨 삼성, 갤럭시 A36으로 韓 시장 방어 나선다",
        "date": "2025-06-02 16:00",
        "link": "https://n.news.naver.com/mnews/article/014/0005358147?sid=105"
    },
    {
        "title": "삼성페이 3시간 넘게 일부 장애…“해킹 아닌 네트워크 문제”",
        "date": "2025-06-02 15:58",
        "link": "https://n.news.naver.com/mnews/article/011/0004492663?sid=105"
    },
    {
        "title": "스마트홈도 AI 전환 11조 시장 잡아라",
        "date": "2025-06-02 15:55",
        "link": "https://n.news.naver.com/mnews/article/018/0006029854?sid=105"
    },
    {
        "title": "삼성전자 '갤럭시링' 요술반지로 만든다, 노태문 XR부터 모바일·스마트...",
        "date": "2025-06-02 15:46",
        "link": "https://www.businesspost.co.kr/BP?command=article_view&num=397637"
    },
    {
        "title": "관세 피한 삼성 '갤럭시 엣지' 美 상륙...새 폴더블의 운명은",
        "date": "2025-06-02 15:43",
        "link": "https://www.newspim.com/news/view/20250602000857"
    },
    {
        "title": "[어바웃 C] '구원등판' 정철동 LGD 사장, '적자 탈출' 연간 턴어라운드 ...",
        "date": "2025-06-02 15:32",
        "link": "https://n.news.naver.com/mnews/article/293/0000068118?sid=101"
    },
    {
        "title": "2나노 파운드리 경쟁 막오른다…내실 다지는 삼성",
        "date": "2025-06-02 15:21",
        "link": "https://n.news.naver.com/mnews/article/018/0006029805?sid=101"
    },
    {
        "title": "구글, 10년 만에 스마트안경 '재도전'...경쟁자는 메타·애플",
        "date": "2025-06-02 15:16",
        "link": "http://www.dailypop.kr/news/articleView.html?idxno=88481"
    },
    {
        "title": "삼성전자, 엑시노스 품은 폴더블폰 출격…하반기 역전 노린다",
        "date": "2025-06-02 15:02",
        "link": "https://daily.hankooki.com/news/articleView.html?idxno=1224444"
    },
    {
        "title": "[단독] 삼성 초슬림폰 갤S25 엣지는 '메이드 인 구미'",
        "date": "2025-06-02 15:00",
        "link": "https://n.news.naver.com/mnews/article/031/0000937214?sid=105"
    },
    {
        "title": "[영상] 해성옵틱스, 올해 삼성전기향 매출 목표 40% 올린 이유",
        "date": "2025-06-02 15:00",
        "link": "http://www.thelec.kr/news/articleView.html?idxno=36645"
    },
    {
        "title": "FC 모바일 출시 5주년…애플과 협업으로 이용자경험 강화",
        "date": "2025-06-02 14:42",
        "link": "https://n.news.naver.com/mnews/article/001/0015426897?sid=105"
    },
    {
        "title": "삼성전자, 하반기 신제품 '갤럭시 Z플립7·Z폴드7' 공개 임박",
        "date": "2025-06-02 14:42",
        "link": "http://www.seouleconews.com/news/articleView.html?idxno=83881"
    },
    {
        "title": "[특징주] 아이씨에이치, 애플 아이폰 공급망 확대 기대…美 친환경 인증...",
        "date": "2025-06-02 14:34",
        "link": "https://www.financialpost.co.kr/news/articleView.html?idxno=227518"
    },
    {
        "title": "LG전자, TV '세계 1위' 수성 가능할까…'저가' 中업체 맹추격",
        "date": "2025-06-02 14:28",
        "link": "https://n.news.naver.com/mnews/article/117/0003949486?sid=105"
    },
    {
        "title": "[공시속보] 영우디에스피, 삼성디스플레이와 339억원 장비공급 계약→매...",
        "date": "2025-06-02 14:18",
        "link": "https://www.topstarnews.net/news/articleView.html?idxno=15684962"
    },
    {
        "title": "iOS 19 대신 26으로? 애플, 운영체제 작명법 전부 바꾼다",
        "date": "2025-06-02 14:00",
        "link": "https://www.autodaily.co.kr/news/articleView.html?idxno=531774"
    },
    {
        "title": "애플워치 SE3·시리즈11·울트라3, 9월 출시 성능 변화는",
        "date": "2025-06-02 13:52",
        "link": "https://www.jemin.com/news/articleView.html?idxno=807837"
    },
    {
        "title": "애플, 아이폰 연도 네이밍 가능성 낮아",
        "date": "2025-06-02 13:50",
        "link": "https://www.jemin.com/news/articleView.html?idxno=807836"
    },
    {
        "title": "애플 앱스토어, 2024년 투명성 보고서 발표",
        "date": "2025-06-02 13:46",
        "link": "https://www.jemin.com/news/articleView.html?idxno=807834"
    },
    {
        "title": "애플 글래스, 에어팟과 차별화된 사회적 수용성",
        "date": "2025-06-02 13:42",
        "link": "https://www.jemin.com/news/articleView.html?idxno=807830"
    },
    {
        "title": "애플 WWDC 2025, AI 신기술 공개 예정",
        "date": "2025-06-02 13:42",
        "link": "https://www.jemin.com/news/articleView.html?idxno=807828"
    },
    {
        "title": "애플 헬스케어 프로젝트 출시 연기",
        "date": "2025-06-02 13:36",
        "link": "https://www.jemin.com/news/articleView.html?idxno=807825"
    },
    {
        "title": "게임사 대상 구글·애플 앱마켓 수수료 환수·인하 설명회 성황리 개최",
        "date": "2025-06-02 13:26",
        "link": "https://n.news.naver.com/mnews/article/030/0003318082?sid=101"
    },
    {
        "title": "'물러설 수 없다' 삼성D-BOE 특허소송 격화",
        "date": "2025-06-02 13:25",
        "link": "https://n.news.naver.com/mnews/article/030/0003318075?sid=105"
    },
    {
        "title": "인도냐? 미국이냐?...애플의 선택은",
        "date": "2025-06-02 13:20",
        "link": "https://science.ytn.co.kr/program/view.php?mcd=0082&hcd=&key=202506021110187770"
    },
    {
        "title": "애플, 2026년 이후 아이폰·아이패드·애플워치에 햅틱 버튼 도입 가능성",
        "date": "2025-06-02 13:16",
        "link": "https://www.jemin.com/news/articleView.html?idxno=807810"
    },
    {
        "title": "아이폰의 매력, 안드로이드와 차별화된 생태계",
        "date": "2025-06-02 13:08",
        "link": "https://www.jemin.com/news/articleView.html?idxno=807800"
    },
    {
        "title": "[新경영 잇는 NEW 삼성③] AI·반도체 다지고 '다시 초격차' 먹거리 발굴",
        "date": "2025-06-02 12:52",
        "link": "https://www.ebn.co.kr/news/articleView.html?idxno=1664961"
    },
    {
        "title": "실적 고공행진 샤오미…트럼프 악재에 주춤대는 애플",
        "date": "2025-06-02 12:26",
        "link": "https://news.einfomax.co.kr/news/articleView.html?idxno=4358487"
    },
    {
        "title": "애플, 2026년 초 아이폰 17e 선보인다... 삼성 갤럭시 S26 등 상반기 프리...",
        "date": "2025-06-02 12:04",
        "link": "https://kr.aving.net/news/articleView.html?idxno=1800671"
    },
    {
        "title": "HMD, 애플보다 먼저 카메라 내장된 스마트워치 출시하나",
        "date": "2025-06-02 11:54",
        "link": "https://kbench.com/?q=node/268009"
    },
    {
        "title": "'7월 공개' 삼성 갤럭시Z플립7·폴드7, 어떻게 달라질까",
        "date": "2025-06-02 11:49",
        "link": "https://n.news.naver.com/mnews/article/629/0000395158?sid=105"
    },
    {
        "title": "애플, 올해 WWDC서 AI 업데이트 발표 생략하는 이유는?",
        "date": "2025-06-02 11:28",
        "link": "https://kr.aving.net/news/articleView.html?idxno=1800668"
    },
    {
        "title": "애플 '아이폰17e' 내년에 ?… “A19 칩셋에 C2 모뎀 장착”",
        "date": "2025-06-02 11:12",
        "link": "https://n.news.naver.com/mnews/article/030/0003318022?sid=104"
    },
    {
        "title": "갤럭시 S26에 퍼블렉시티AI 탑재될까…양사합의 근접",
        "date": "2025-06-02 11:05",
        "link": "https://n.news.naver.com/mnews/article/018/0006029636?sid=101"
    },
    {
        "title": "애플 iOS 19/26의 주요 변화: 비전OS 새 UI와 시리의 변화",
        "date": "2025-06-02 10:54",
        "link": "https://www.betanews.net/article/view/beta202506020001"
    },
    {
        "title": "아이폰 vs. 안드로이드…아이폰 이용자가 바꾸지 않는 이유",
        "date": "2025-06-02 10:52",
        "link": "https://www.digitaltoday.co.kr/news/articleView.html?idxno=569056"
    },
    {
        "title": "삼성, 갤럭시 S22 시리즈 등 3년 전 모델에도 One UI 8 베타 제공한다......",
        "date": "2025-06-02 10:48",
        "link": "https://kr.aving.net/news/articleView.html?idxno=1800662"
    },
    {
        "title": "2026년 아이폰·아이패드·애플워치, 햅틱 버튼 도입 가능성",
        "date": "2025-06-02 10:46",
        "link": "https://www.digitaltoday.co.kr/news/articleView.html?idxno=569045"
    },
    {
        "title": "“이 남자 때문에, 0%대 성장 폭삭”…전세계 스마트폰 시장에 ‘비상등...",
        "date": "2025-06-02 10:34",
        "link": "https://n.news.naver.com/mnews/article/009/0005502285?sid=101"
    },
    {
        "title": "삼성전자, 갤S26에 美스타트업 퍼플렉시티AI 탑재 검토",
        "date": "2025-06-02 10:28",
        "link": "https://n.news.naver.com/mnews/article/011/0004492527?sid=101"
    },
    {
        "title": "애플 글래스, 에어팟과 차별화된 강점…'사회적 수용성' 용이",
        "date": "2025-06-02 10:06",
        "link": "https://www.digitaltoday.co.kr/news/articleView.html?idxno=569016"
    },
    {
        "title": "AI로 건강관리? 애플 헬스케어 프로젝트 2026년으로 연기",
        "date": "2025-06-02 10:06",
        "link": "https://www.digitaltoday.co.kr/news/articleView.html?idxno=569019"
    },
    {
        "title": "애플, 2024년 앱스토어 투명성 보고서 발표…앱 삭제 40% 감소",
        "date": "2025-06-02 10:06",
        "link": "https://www.digitaltoday.co.kr/news/articleView.html?idxno=569014"
    },
    {
        "title": "애플 WWDC서 AI 신기술 공개 예정…내부 반응은 미지근",
        "date": "2025-06-02 10:06",
        "link": "https://www.digitaltoday.co.kr/news/articleView.html?idxno=569013"
    },
    {
        "title": "애플워치 SE3·시리즈11·울트라3, 9월 출시…성능 변화는?",
        "date": "2025-06-02 10:04",
        "link": "https://www.digitaltoday.co.kr/news/articleView.html?idxno=569005"
    },
    {
        "title": "애플 아이폰 이름에도 연도 붙일까…가능성 낮아",
        "date": "2025-06-02 10:04",
        "link": "https://www.digitaltoday.co.kr/news/articleView.html?idxno=569009"
    },
    {
        "title": "애플, 차세대 맥OS 26 '타호'로 명명…디자인 혁신 예고",
        "date": "2025-06-02 10:02",
        "link": "https://www.digitaltoday.co.kr/news/articleView.html?idxno=569001"
    },
    {
        "title": "애플워치 울트라2 vs 갤럭시워치 울트라, GPS 정확도는 애플이 40% 앞서",
        "date": "2025-06-02 09:50",
        "link": "http://www.g-enews.com/ko-kr/news/article/news_all/202506020938059712fbbec65dfb_1/article.html"
    },
    {
        "title": "애플 AI 전략 '멈칫'…WWDC서도 '준비중' 펫말 달까",
        "date": "2025-06-02 09:01",
        "link": "https://n.news.naver.com/mnews/article/138/0002197761?sid=105"
    },
    {
        "title": "‘AI 강화’ 갤럭시냐, ‘고혈압 감지’ 애플이냐… 하반기 스마트워치...",
        "date": "2025-06-02 09:00",
        "link": "https://n.news.naver.com/mnews/article/021/0002713434?sid=105"
    },
    {
        "title": "애플 아이폰17e 준비 중…SE 후속 라인업 변화 예고",
        "date": "2025-06-02 09:00",
        "link": "https://www.digitaltoday.co.kr/news/articleView.html?idxno=568981"
    },
    {
        "title": "퀴즈노스, 달콤 상큼한 '애플망고 리코타 샌드위치' 출시",
        "date": "2025-06-02 09:00",
        "link": "https://www.itbiznews.com/news/articleView.html?idxno=170533"
    },
    {
        "title": "덕산네오룩스, OLED 소재 강자로 재부상...목표가 5만원 유지",
        "date": "2025-06-02 08:48",
        "link": "http://www.globalepic.co.kr/view.php?ud=2025060208421826445ebfd494dd_29"
    },
    {
        "title": "메리츠證 파인엠텍, 북미 세트사의 폴더블 시장 참여 수혜 기대",
        "date": "2025-06-02 08:44",
        "link": "https://n.news.naver.com/mnews/article/014/0005357782?sid=101"
    },
    {
        "title": "[핀포인트] [삼성디스플레이] 전자, 올해도 손 벌릴까",
        "date": "2025-06-02 08:08",
        "link": "https://news.dealsitetv.com/articles/154983"
    },
    {
        "title": "아이폰16, 전 세계 싹쓸이…갤럭시는 밀렸다",
        "date": "2025-06-02 07:30",
        "link": "https://www.newswhoplus.com/news/articleView.html?idxno=28853"
    },
    {
        "title": "체질개선 박차 가하는 LGD, 인력 효율화 나서",
        "date": "2025-06-02 07:16",
        "link": "https://dealsite.co.kr/articles/142447"
    },
    {
        "title": "[핀포인트] [삼성디스플레이] 투자는 예년 수준…쌓이는 현금",
        "date": "2025-06-02 07:02",
        "link": "https://news.dealsitetv.com/articles/154958"
    },
    {
        "title": "[핀포인트] [삼성디스플레이] 미국 관세 유탄 맞은 베트남 투자",
        "date": "2025-06-02 07:02",
        "link": "https://news.dealsitetv.com/articles/155035"
    },
    {
        "title": "[DDI사 점검] LX세미콘, 하반기 OLED 아이패드 납품 기대",
        "date": "2025-06-02 07:02",
        "link": "https://dealsite.co.kr/articles/142371"
    }
]